<?xml version = '1.0' encoding = 'UTF-8'?>
<Relation class="oracle.dbtools.crest.model.design.logical.Relation" name="Relation_21" directorySegmentName="seg_0" id="7E946F15-FA72-F1CC-5394-D15B9F17392E">
<createdBy>User</createdBy>
<createdTime>2022-03-14 16:32:51 UTC</createdTime>
<ownerDesignName>3.3_ex2</ownerDesignName>
<engineerTo>
<item key="819CDA61-46AA-4D55-114A-414AD32AC9C1" value="true"/>
</engineerTo>
<sourcePk>6BE6AA0E-8070-1E7B-FBD4-4255762FDFA4</sourcePk>
<identifying>true</identifying>
<nameOnSource>have </nameOnSource>
<nameOnTarget>be for</nameOnTarget>
<optionalSource>true</optionalSource>
<optionalTarget>false</optionalTarget>
<sourceCardinality>1</sourceCardinality>
<sourceEntity>54ACA946-FBBD-9DE7-1999-405D24E41B00</sourceEntity>
<targetCardinalityString>*</targetCardinalityString>
<targetEntity>DA74E828-3708-6ECF-CD1A-50C99A6E2614</targetEntity>
<transferable>true</transferable>
<deleteRule>NO ACTION</deleteRule>
</Relation>